pytincture/__init__.py
pytincture/dataclass.py
pytincture/backend/__init__.py
pytincture/backend/app.py
pytincture/frontend/index.html
pytincture/frontend/pytincture.js
scripts/read_framework_version.py
tests/test_app.py
tests/test_dataclass.py
tests/test_launcher.py
pytincture-0.9.27.dist-info/METADATA
pytincture-0.9.27.dist-info/WHEEL
pytincture-0.9.27.dist-info/top_level.txt
pytincture-0.9.27.dist-info/RECORD
