Metadata-Version: 2.4
Name: pytincture
Version: 0.9.27
Summary: UI Builder
Author-email: Your Name <schapman1974@gmail.com>
License: MIT
Project-URL: Homepage, https://github.com/pytincture/pytincture
Requires-Dist: aiofiles==25.1.0
Requires-Dist: fastapi==0.128.0
Requires-Dist: fastmcp==2.13.0.1
Requires-Dist: upstash-redis>=1.2.0
Requires-Dist: pyyaml==6.0.3
Requires-Dist: requests==2.32.5
Requires-Dist: uvicorn==0.40.0
Requires-Dist: wheel==0.45.1
Requires-Dist: js==1.0
Requires-Dist: pyodide-py==0.29.1
Requires-Dist: authlib==1.6.6
Requires-Dist: python-dotenv==1.1.1
Requires-Dist: aioredis==2.0.1
Requires-Dist: pytest==8.4.2
Requires-Dist: nest-asyncio==1.6.0
Requires-Dist: python3-saml==1.16.0
Requires-Dist: markupsafe==3.0.3
Requires-Dist: itsdangerous==2.2.0
Requires-Dist: python-multipart==0.0.20
Requires-Dist: xmlsec>=1.3.17
